kbot_client/__init__.py
kbot_client/callback_chat.py
kbot_client/chatbot_client/__init__.py
kbot_client/chatbot_client/chat_client.py
kbot_client/chatbot_client/chat_client_2.py
kbot_client/client.py
kbot_client/client_group.py
kbot_client/folder_sync.py
kbot_client/test.py
kbot_py_client-2.1.2.dist-info/LICENSE
kbot_py_client-2.1.2.dist-info/METADATA
kbot_py_client-2.1.2.dist-info/WHEEL
kbot_py_client-2.1.2.dist-info/RECORD
