Metadata-Version: 2.3
Name: kbot-py-client
Version: 2.1.2
Summary: Client for Konverso Kbot.
License: MIT
Author: Konverso
Author-email: contact@konverso.ai
Requires-Python: >=3.10
Classifier: License :: OSI Approved :: MIT License
Classifier: Operating System :: OS Independent
Classifier: Programming Language :: Python :: 3
Classifier: Programming Language :: Python :: 3.10
Classifier: Programming Language :: Python :: 3.11
Classifier: Programming Language :: Python :: 3.12
Classifier: Programming Language :: Python :: 3.13
Requires-Dist: requests (>=2.27.1)
Project-URL: Homepage, https://www.konverso.ai/
Project-URL: Source, https://github.com/konverso-ai/kbot-py-client
